{
   
    "total": "12",
    "rows": [
         {
            "gps_alarm": "dedffhhh",
            "preheat_status": "state",
            "acc_padel_position": "0.0",
            "location": "shenzhne",
            "oil_pump_motor_tempera": "hahdn",
            "engine_oil_temperature": "40",
            "middle_bit": "999",
            "fuel_temperature": "332",
            "lock_status": "0",
            "pull_time": "0",
            "hard_id": "12660503004",
            "driver_id": "09098777",
            "longitude": "119.8736887836121",
            "fuel_consumption": "0.00",
            "client_id": "33143",
            "department_name": "XX叉车有限公司",
            "manifold_temperature": "78",
            "vid": "68505811",
            "region_alarm": "kdhbfk",
            "collision": "0.00",
            "r_longitude": "119.869080",
            "pump_time": "0",
            "gps_no": "2660503004",
            "serious_fault": "fd",
            "water_temperature": "32",
            "brake_pressure_alarm": "0",
            "handler_push": "engine_speed",
            "department_no": "001002",
            "device_power": "41.00",
            "average_fuel": "0.00",
            "promary_id": "322",
            "repair_info": "890",
            "can_speed": "00",
            "latitude": "30.26662102659477",
            "work_hours": "0.0",
            "car_sn": "AAAAAAAAA",
            "engine_speed": "0.0",
            "company_id": "2",
            "weight": "0.00",
            "driver_name": "fdfdv",
            "can_error_code": "202",
            "v_type": "2",
            "pump_control_temperature": "33",
            "fuel_tempera_alarm": "0",
            "city_id": "1234",
            "r_latitude": "30.269243",
            "speedlimit_status": "0",
            "da_up": "2016-10-20 13:33:43",
            "fuel_press_alarm": "0",
            "coolant_temperature": "000",
            "hd_type_no": "CPD50J-C2",
            "air_filter": "676"
        },
         {
            "gps_alarm": "dedffhhh",
            "preheat_status": "state",
            "acc_padel_position": "0.0",
            "location": "shenzhne",
            "oil_pump_motor_tempera": "hahdn",
            "engine_oil_temperature": "40",
            "middle_bit": "999",
            "fuel_temperature": "332",
            "lock_status": "0",
            "pull_time": "0",
            "hard_id": "12660503004",
            "driver_id": "09098777",
            "longitude": "119.8736887836121",
            "fuel_consumption": "0.00",
            "client_id": "33143",
            "department_name": "XX叉车有限公司",
            "manifold_temperature": "78",
            "vid": "68505811",
            "region_alarm": "kdhbfk",
            "collision": "0.00",
            "r_longitude": "119.869080",
            "pump_time": "0",
            "gps_no": "2660503004",
            "serious_fault": "fd",
            "water_temperature": "32",
            "brake_pressure_alarm": "0",
            "handler_push": "engine_speed",
            "department_no": "001002",
            "device_power": "41.00",
            "average_fuel": "0.00",
            "promary_id": "322",
            "repair_info": "890",
            "can_speed": "00",
            "latitude": "30.26662102659477",
            "work_hours": "0.0",
            "car_sn": "AAAAAAAAA",
            "engine_speed": "0.0",
            "company_id": "2",
            "weight": "0.00",
            "driver_name": "fdfdv",
            "can_error_code": "202",
            "v_type": "2",
            "pump_control_temperature": "33",
            "fuel_tempera_alarm": "0",
            "city_id": "1234",
            "r_latitude": "30.269243",
            "speedlimit_status": "0",
            "da_up": "2016-10-20 13:33:43",
            "fuel_press_alarm": "0",
            "coolant_temperature": "000",
            "hd_type_no": "CPD50J-C2",
            "air_filter": "676"
        },
         {
            "gps_alarm": "dedffhhh",
            "preheat_status": "state",
            "acc_padel_position": "0.0",
            "location": "shenzhne",
            "oil_pump_motor_tempera": "hahdn",
            "engine_oil_temperature": "40",
            "middle_bit": "999",
            "fuel_temperature": "332",
            "lock_status": "0",
            "pull_time": "0",
            "hard_id": "12660503004",
            "driver_id": "09098777",
            "longitude": "119.8736887836121",
            "fuel_consumption": "0.00",
            "client_id": "33143",
            "department_name": "XX叉车有限公司",
            "manifold_temperature": "78",
            "vid": "68505811",
            "region_alarm": "kdhbfk",
            "collision": "0.00",
            "r_longitude": "119.869080",
            "pump_time": "0",
            "gps_no": "2660503004",
            "serious_fault": "fd",
            "water_temperature": "32",
            "brake_pressure_alarm": "0",
            "handler_push": "engine_speed",
            "department_no": "001002",
            "device_power": "41.00",
            "average_fuel": "0.00",
            "promary_id": "322",
            "repair_info": "890",
            "can_speed": "00",
            "latitude": "30.26662102659477",
            "work_hours": "0.0",
            "car_sn": "AAAAAAAAA",
            "engine_speed": "0.0",
            "company_id": "2",
            "weight": "0.00",
            "driver_name": "fdfdv",
            "can_error_code": "202",
            "v_type": "2",
            "pump_control_temperature": "33",
            "fuel_tempera_alarm": "0",
            "city_id": "1234",
            "r_latitude": "30.269243",
            "speedlimit_status": "0",
            "da_up": "2016-10-20 13:33:43",
            "fuel_press_alarm": "0",
            "coolant_temperature": "000",
            "hd_type_no": "CPD50J-C2",
            "air_filter": "676"
        },
         {
            "gps_alarm": "dedffhhh",
            "preheat_status": "state",
            "acc_padel_position": "0.0",
            "location": "shenzhne",
            "oil_pump_motor_tempera": "hahdn",
            "engine_oil_temperature": "40",
            "middle_bit": "999",
            "fuel_temperature": "332",
            "lock_status": "0",
            "pull_time": "0",
            "hard_id": "12660503004",
            "driver_id": "09098777",
            "longitude": "119.8736887836121",
            "fuel_consumption": "0.00",
            "client_id": "33143",
            "department_name": "XX叉车有限公司",
            "manifold_temperature": "78",
            "vid": "68505811",
            "region_alarm": "kdhbfk",
            "collision": "0.00",
            "r_longitude": "119.869080",
            "pump_time": "0",
            "gps_no": "2660503004",
            "serious_fault": "fd",
            "water_temperature": "32",
            "brake_pressure_alarm": "0",
            "handler_push": "engine_speed",
            "department_no": "001002",
            "device_power": "41.00",
            "average_fuel": "0.00",
            "promary_id": "322",
            "repair_info": "890",
            "can_speed": "00",
            "latitude": "30.26662102659477",
            "work_hours": "0.0",
            "car_sn": "AAAAAAAAA",
            "engine_speed": "0.0",
            "company_id": "2",
            "weight": "0.00",
            "driver_name": "fdfdv",
            "can_error_code": "202",
            "v_type": "2",
            "pump_control_temperature": "33",
            "fuel_tempera_alarm": "0",
            "city_id": "1234",
            "r_latitude": "30.269243",
            "speedlimit_status": "0",
            "da_up": "2016-10-20 13:33:43",
            "fuel_press_alarm": "0",
            "coolant_temperature": "000",
            "hd_type_no": "CPD50J-C2",
            "air_filter": "676"
        },
         {
            "gps_alarm": "dedffhhh",
            "preheat_status": "state",
            "acc_padel_position": "0.0",
            "location": "shenzhne",
            "oil_pump_motor_tempera": "hahdn",
            "engine_oil_temperature": "40",
            "middle_bit": "999",
            "fuel_temperature": "332",
            "lock_status": "0",
            "pull_time": "0",
            "hard_id": "12660503004",
            "driver_id": "09098777",
            "longitude": "119.8736887836121",
            "fuel_consumption": "0.00",
            "client_id": "33143",
            "department_name": "XX叉车有限公司",
            "manifold_temperature": "78",
            "vid": "68505811",
            "region_alarm": "kdhbfk",
            "collision": "0.00",
            "r_longitude": "119.869080",
            "pump_time": "0",
            "gps_no": "2660503004",
            "serious_fault": "fd",
            "water_temperature": "32",
            "brake_pressure_alarm": "0",
            "handler_push": "engine_speed",
            "department_no": "001002",
            "device_power": "41.00",
            "average_fuel": "0.00",
            "promary_id": "322",
            "repair_info": "890",
            "can_speed": "00",
            "latitude": "30.26662102659477",
            "work_hours": "0.0",
            "car_sn": "AAAAAAAAA",
            "engine_speed": "0.0",
            "company_id": "2",
            "weight": "0.00",
            "driver_name": "fdfdv",
            "can_error_code": "202",
            "v_type": "2",
            "pump_control_temperature": "33",
            "fuel_tempera_alarm": "0",
            "city_id": "1234",
            "r_latitude": "30.269243",
            "speedlimit_status": "0",
            "da_up": "2016-10-20 13:33:43",
            "fuel_press_alarm": "0",
            "coolant_temperature": "000",
            "hd_type_no": "CPD50J-C2",
            "air_filter": "676"
        },
         {
            "gps_alarm": "dedffhhh",
            "preheat_status": "state",
            "acc_padel_position": "0.0",
            "location": "shenzhne",
            "oil_pump_motor_tempera": "hahdn",
            "engine_oil_temperature": "40",
            "middle_bit": "999",
            "fuel_temperature": "332",
            "lock_status": "0",
            "pull_time": "0",
            "hard_id": "12660503004",
            "driver_id": "09098777",
            "longitude": "119.8736887836121",
            "fuel_consumption": "0.00",
            "client_id": "33143",
            "department_name": "XX叉车有限公司",
            "manifold_temperature": "78",
            "vid": "68505811",
            "region_alarm": "kdhbfk",
            "collision": "0.00",
            "r_longitude": "119.869080",
            "pump_time": "0",
            "gps_no": "2660503004",
            "serious_fault": "fd",
            "water_temperature": "32",
            "brake_pressure_alarm": "0",
            "handler_push": "engine_speed",
            "department_no": "001002",
            "device_power": "41.00",
            "average_fuel": "0.00",
            "promary_id": "322",
            "repair_info": "890",
            "can_speed": "00",
            "latitude": "30.26662102659477",
            "work_hours": "0.0",
            "car_sn": "AAAAAAAAA",
            "engine_speed": "0.0",
            "company_id": "2",
            "weight": "0.00",
            "driver_name": "fdfdv",
            "can_error_code": "202",
            "v_type": "2",
            "pump_control_temperature": "33",
            "fuel_tempera_alarm": "0",
            "city_id": "1234",
            "r_latitude": "30.269243",
            "speedlimit_status": "0",
            "da_up": "2016-10-20 13:33:43",
            "fuel_press_alarm": "0",
            "coolant_temperature": "000",
            "hd_type_no": "CPD50J-C2",
            "air_filter": "676"
        },
         {
            "gps_alarm": "dedffhhh",
            "preheat_status": "state",
            "acc_padel_position": "0.0",
            "location": "shenzhne",
            "oil_pump_motor_tempera": "hahdn",
            "engine_oil_temperature": "40",
            "middle_bit": "999",
            "fuel_temperature": "332",
            "lock_status": "0",
            "pull_time": "0",
            "hard_id": "12660503004",
            "driver_id": "09098777",
            "longitude": "119.8736887836121",
            "fuel_consumption": "0.00",
            "client_id": "33143",
            "department_name": "XX叉车有限公司",
            "manifold_temperature": "78",
            "vid": "68505811",
            "region_alarm": "kdhbfk",
            "collision": "0.00",
            "r_longitude": "119.869080",
            "pump_time": "0",
            "gps_no": "2660503004",
            "serious_fault": "fd",
            "water_temperature": "32",
            "brake_pressure_alarm": "0",
            "handler_push": "engine_speed",
            "department_no": "001002",
            "device_power": "41.00",
            "average_fuel": "0.00",
            "promary_id": "322",
            "repair_info": "890",
            "can_speed": "00",
            "latitude": "30.26662102659477",
            "work_hours": "0.0",
            "car_sn": "AAAAAAAAA",
            "engine_speed": "0.0",
            "company_id": "2",
            "weight": "0.00",
            "driver_name": "fdfdv",
            "can_error_code": "202",
            "v_type": "2",
            "pump_control_temperature": "33",
            "fuel_tempera_alarm": "0",
            "city_id": "1234",
            "r_latitude": "30.269243",
            "speedlimit_status": "0",
            "da_up": "2016-10-20 13:33:43",
            "fuel_press_alarm": "0",
            "coolant_temperature": "000",
            "hd_type_no": "CPD50J-C2",
            "air_filter": "676"
        },
         {
            "gps_alarm": "dedffhhh",
            "preheat_status": "state",
            "acc_padel_position": "0.0",
            "location": "shenzhne",
            "oil_pump_motor_tempera": "hahdn",
            "engine_oil_temperature": "40",
            "middle_bit": "999",
            "fuel_temperature": "332",
            "lock_status": "0",
            "pull_time": "0",
            "hard_id": "12660503004",
            "driver_id": "09098777",
            "longitude": "119.8736887836121",
            "fuel_consumption": "0.00",
            "client_id": "33143",
            "department_name": "XX叉车有限公司",
            "manifold_temperature": "78",
            "vid": "68505811",
            "region_alarm": "kdhbfk",
            "collision": "0.00",
            "r_longitude": "119.869080",
            "pump_time": "0",
            "gps_no": "2660503004",
            "serious_fault": "fd",
            "water_temperature": "32",
            "brake_pressure_alarm": "0",
            "handler_push": "engine_speed",
            "department_no": "001002",
            "device_power": "41.00",
            "average_fuel": "0.00",
            "promary_id": "322",
            "repair_info": "890",
            "can_speed": "00",
            "latitude": "30.26662102659477",
            "work_hours": "0.0",
            "car_sn": "AAAAAAAAA",
            "engine_speed": "0.0",
            "company_id": "2",
            "weight": "0.00",
            "driver_name": "fdfdv",
            "can_error_code": "202",
            "v_type": "2",
            "pump_control_temperature": "33",
            "fuel_tempera_alarm": "0",
            "city_id": "1234",
            "r_latitude": "30.269243",
            "speedlimit_status": "0",
            "da_up": "2016-10-20 13:33:43",
            "fuel_press_alarm": "0",
            "coolant_temperature": "000",
            "hd_type_no": "CPD50J-C2",
            "air_filter": "676"
        },
         {
            "gps_alarm": "dedffhhh",
            "preheat_status": "state",
            "acc_padel_position": "0.0",
            "location": "shenzhne",
            "oil_pump_motor_tempera": "hahdn",
            "engine_oil_temperature": "40",
            "middle_bit": "999",
            "fuel_temperature": "332",
            "lock_status": "0",
            "pull_time": "0",
            "hard_id": "12660503004",
            "driver_id": "09098777",
            "longitude": "119.8736887836121",
            "fuel_consumption": "0.00",
            "client_id": "33143",
            "department_name": "XX叉车有限公司",
            "manifold_temperature": "78",
            "vid": "68505811",
            "region_alarm": "kdhbfk",
            "collision": "0.00",
            "r_longitude": "119.869080",
            "pump_time": "0",
            "gps_no": "2660503004",
            "serious_fault": "fd",
            "water_temperature": "32",
            "brake_pressure_alarm": "0",
            "handler_push": "engine_speed",
            "department_no": "001002",
            "device_power": "41.00",
            "average_fuel": "0.00",
            "promary_id": "322",
            "repair_info": "890",
            "can_speed": "00",
            "latitude": "30.26662102659477",
            "work_hours": "0.0",
            "car_sn": "AAAAAAAAA",
            "engine_speed": "0.0",
            "company_id": "2",
            "weight": "0.00",
            "driver_name": "fdfdv",
            "can_error_code": "202",
            "v_type": "2",
            "pump_control_temperature": "33",
            "fuel_tempera_alarm": "0",
            "city_id": "1234",
            "r_latitude": "30.269243",
            "speedlimit_status": "0",
            "da_up": "2016-10-20 13:33:43",
            "fuel_press_alarm": "0",
            "coolant_temperature": "000",
            "hd_type_no": "CPD50J-C2",
            "air_filter": "676"
        },
         {
            "gps_alarm": "dedffhhh",
            "preheat_status": "state",
            "acc_padel_position": "0.0",
            "location": "shenzhne",
            "oil_pump_motor_tempera": "hahdn",
            "engine_oil_temperature": "40",
            "middle_bit": "999",
            "fuel_temperature": "332",
            "lock_status": "0",
            "pull_time": "0",
            "hard_id": "12660503004",
            "driver_id": "09098777",
            "longitude": "119.8736887836121",
            "fuel_consumption": "0.00",
            "client_id": "33143",
            "department_name": "XX叉车有限公司",
            "manifold_temperature": "78",
            "vid": "68505811",
            "region_alarm": "kdhbfk",
            "collision": "0.00",
            "r_longitude": "119.869080",
            "pump_time": "0",
            "gps_no": "2660503004",
            "serious_fault": "fd",
            "water_temperature": "32",
            "brake_pressure_alarm": "0",
            "handler_push": "engine_speed",
            "department_no": "001002",
            "device_power": "41.00",
            "average_fuel": "0.00",
            "promary_id": "322",
            "repair_info": "890",
            "can_speed": "00",
            "latitude": "30.26662102659477",
            "work_hours": "0.0",
            "car_sn": "AAAAAAAAA",
            "engine_speed": "0.0",
            "company_id": "2",
            "weight": "0.00",
            "driver_name": "fdfdv",
            "can_error_code": "202",
            "v_type": "2",
            "pump_control_temperature": "33",
            "fuel_tempera_alarm": "0",
            "city_id": "1234",
            "r_latitude": "30.269243",
            "speedlimit_status": "0",
            "da_up": "2016-10-20 13:33:43",
            "fuel_press_alarm": "0",
            "coolant_temperature": "000",
            "hd_type_no": "CPD50J-C2",
            "air_filter": "676"
        } 
    ]
}